{
  "manifestVersion": "3.2",
  "admin": {
    "address": "0x854Aeba4b5CB1e84AD32a84B77c82e82E23f3C13",
    "txHash": "0xc07ce927ca9fdfe02227bae3967d0558334255fe6812da739f74e3e831e1a9a0"
  },
  "proxies": [
    {
      "address": "0xa8abA6bB110745e079Ad90cbbAF62102c8bA80Fe",
      "txHash": "0x58327a223f1c0055c1ba2700fa25c331d3efa328e4187b85dfa6b7951b6ef6f5",
      "kind": "transparent"
    },
    {
      "address": "0xf79A52F50d3abF4ff33F03B93e208C4d05685357",
      "txHash": "0x3c4be473422954f3e3abb65b3a08fe819dc2546a71bea8adcd7751fdbe8570ce",
      "kind": "transparent"
    },
    {
      "address": "0x9Bec796560fE43b90aD6501E538F6a9Ff1d5A610",
      "txHash": "0x5db1a63075fa49e67784d28a936d16d5133800b86efaf3ae006082486b0ecd58",
      "kind": "transparent"
    },
    {
      "address": "0x87E1570667b71Ee05503f5d326B69DC93cC041bf",
      "txHash": "0x4b9c97ef1d45ccca1880b81683383d2d88bc2e8c2d03584e40b7ffaad5ea786a",
      "kind": "transparent"
    },
    {
      "address": "0x3e10C029d300483b7b0b9642ECe923ef61bBB9ab",
      "txHash": "0x6b503e400f23abbe281273c83de8d531b54e648be9bee79c4a5a7e749ce21b73",
      "kind": "transparent"
    }
  ],
  "impls": {
    "cebd5e9384a85e0b3065120e5d47ccad37f301794769893a98460293bf9d5a5d": {
      "address": "0x2A90147BF1eB707321BcBa0F39b2D7e3768968c7",
      "txHash": "0x037ea6192838de2aa8717ff6b294ffd30c330dcf48435fe855c66728a2eb6a68",
      "layout": {
        "storage": [
          {
            "contract": "Initializable",
            "label": "_initialized",
            "type": "t_bool",
            "src": "../@openzeppelin/contracts-upgradeable/proxy/Initializable.sol:25"
          },
          {
            "contract": "Initializable",
            "label": "_initializing",
            "type": "t_bool",
            "src": "../@openzeppelin/contracts-upgradeable/proxy/Initializable.sol:30"
          },
          {
            "contract": "ContextUpgradeable",
            "label": "__gap",
            "type": "t_array(t_uint256)50_storage",
            "src": "../@openzeppelin/contracts-upgradeable/utils/ContextUpgradeable.sol:31"
          },
          {
            "contract": "ERC165Upgradeable",
            "label": "_supportedInterfaces",
            "type": "t_mapping(t_bytes4,t_bool)",
            "src": "../@openzeppelin/contracts-upgradeable/introspection/ERC165Upgradeable.sol:23"
          },
          {
            "contract": "ERC165Upgradeable",
            "label": "__gap",
            "type": "t_array(t_uint256)49_storage",
            "src": "../@openzeppelin/contracts-upgradeable/introspection/ERC165Upgradeable.sol:59"
          },
          {
            "contract": "ERC721Upgradeable",
            "label": "_holderTokens",
            "type": "t_mapping(t_address,t_struct(UintSet)2844_storage)",
            "src": "../project:/contracts/ERC721Upgradeable.sol:34"
          },
          {
            "contract": "ERC721Upgradeable",
            "label": "_tokenOwners",
            "type": "t_struct(UintToAddressMap)2221_storage",
            "src": "../project:/contracts/ERC721Upgradeable.sol:37"
          },
          {
            "contract": "ERC721Upgradeable",
            "label": "_tokenApprovals",
            "type": "t_mapping(t_uint256,t_address)",
            "src": "../project:/contracts/ERC721Upgradeable.sol:40"
          },
          {
            "contract": "ERC721Upgradeable",
            "label": "_operatorApprovals",
            "type": "t_mapping(t_address,t_mapping(t_address,t_bool))",
            "src": "../project:/contracts/ERC721Upgradeable.sol:43"
          },
          {
            "contract": "ERC721Upgradeable",
            "label": "_name",
            "type": "t_string_storage",
            "src": "../project:/contracts/ERC721Upgradeable.sol:46"
          },
          {
            "contract": "ERC721Upgradeable",
            "label": "_symbol",
            "type": "t_string_storage",
            "src": "../project:/contracts/ERC721Upgradeable.sol:49"
          },
          {
            "contract": "ERC721Upgradeable",
            "label": "_tokenURIs",
            "type": "t_mapping(t_uint256,t_string_storage)",
            "src": "../project:/contracts/ERC721Upgradeable.sol:52"
          },
          {
            "contract": "ERC721Upgradeable",
            "label": "_baseURI",
            "type": "t_string_storage",
            "src": "../project:/contracts/ERC721Upgradeable.sol:55"
          },
          {
            "contract": "ERC721Upgradeable",
            "label": "_burnedTokens",
            "type": "t_mapping(t_uint256,t_bool)",
            "src": "../project:/contracts/ERC721Upgradeable.sol:92"
          },
          {
            "contract": "ERC721Upgradeable",
            "label": "__gap",
            "type": "t_array(t_uint256)40_storage",
            "src": "../project:/contracts/ERC721Upgradeable.sol:494"
          },
          {
            "contract": "ERC721DefaultApproval",
            "label": "defaultApprovals",
            "type": "t_mapping(t_address,t_bool)",
            "src": "../project:/contracts/ERC721DefaultApproval.sol:7"
          },
          {
            "contract": "ERC721DefaultApproval",
            "label": "__gap",
            "type": "t_array(t_uint256)50_storage",
            "src": "../project:/contracts/ERC721DefaultApproval.sol:23"
          },
          {
            "contract": "ERC721BurnableUpgradeable",
            "label": "__gap",
            "type": "t_array(t_uint256)50_storage",
            "src": "../project:/contracts/ERC721BurnableUpgradeable.sol:40"
          },
          {
            "contract": "EIP712Upgradeable",
            "label": "_HASHED_NAME",
            "type": "t_bytes32",
            "src": "../@openzeppelin/contracts-upgradeable/drafts/EIP712Upgradeable.sol:27"
          },
          {
            "contract": "EIP712Upgradeable",
            "label": "_HASHED_VERSION",
            "type": "t_bytes32",
            "src": "../@openzeppelin/contracts-upgradeable/drafts/EIP712Upgradeable.sol:28"
          },
          {
            "contract": "EIP712Upgradeable",
            "label": "__gap",
            "type": "t_array(t_uint256)50_storage",
            "src": "../@openzeppelin/contracts-upgradeable/drafts/EIP712Upgradeable.sol:120"
          },
          {
            "contract": "ERC1271Validator",
            "label": "__gap",
            "type": "t_array(t_uint256)50_storage",
            "src": "../project:/contracts/Mint721Validator.sol:26"
          },
          {
            "contract": "Mint721Validator",
            "label": "__gap",
            "type": "t_array(t_uint256)50_storage",
            "src": "../project:/contracts/Mint721Validator.sol:37"
          },
          {
            "contract": "OwnableUpgradeable",
            "label": "_owner",
            "type": "t_address",
            "src": "../@openzeppelin/contracts-upgradeable/access/OwnableUpgradeable.sol:20"
          },
          {
            "contract": "OwnableUpgradeable",
            "label": "__gap",
            "type": "t_array(t_uint256)49_storage",
            "src": "../@openzeppelin/contracts-upgradeable/access/OwnableUpgradeable.sol:74"
          },
          {
            "contract": "ERC721Lazy",
            "label": "creators",
            "type": "t_mapping(t_uint256,t_address)",
            "src": "../project:/contracts/ERC721Lazy.sol:21"
          },
          {
            "contract": "ERC721Lazy",
            "label": "metasaltToken",
            "type": "t_address",
            "src": "../project:/contracts/ERC721Lazy.sol:22"
          },
          {
            "contract": "ERC721Lazy",
            "label": "MetasaltTokenCreateRewardValue",
            "type": "t_uint256",
            "src": "../project:/contracts/ERC721Lazy.sol:23"
          },
          {
            "contract": "ERC721Lazy",
            "label": "__gap",
            "type": "t_array(t_uint256)50_storage",
            "src": "../project:/contracts/ERC721Lazy.sol:111"
          },
          {
            "contract": "ERC721Base",
            "label": "__gap",
            "type": "t_array(t_uint256)50_storage",
            "src": "../project:/contracts/ERC721Base.sol:26"
          },
          {
            "contract": "ERC721MetaSalt",
            "label": "__gap",
            "type": "t_array(t_uint256)50_storage",
            "src": "../project:/contracts/ERC721MetaSalt.sol:25"
          }
        ],
        "types": {
          "t_array(t_uint256)50_storage": {
            "label": "uint256[50]"
          },
          "t_uint256": {
            "label": "uint256"
          },
          "t_mapping(t_uint256,t_address)": {
            "label": "mapping(uint256 => address)"
          },
          "t_address": {
            "label": "address"
          },
          "t_array(t_uint256)49_storage": {
            "label": "uint256[49]"
          },
          "t_bytes32": {
            "label": "bytes32"
          },
          "t_mapping(t_address,t_bool)": {
            "label": "mapping(address => bool)"
          },
          "t_bool": {
            "label": "bool"
          },
          "t_mapping(t_address,t_struct(UintSet)2844_storage)": {
            "label": "mapping(address => struct EnumerableSetUpgradeable.UintSet)"
          },
          "t_struct(UintSet)2844_storage": {
            "label": "struct EnumerableSetUpgradeable.UintSet",
            "members": [
              {
                "label": "_inner",
                "type": "t_struct(Set)2458_storage"
              }
            ]
          },
          "t_struct(Set)2458_storage": {
            "label": "struct EnumerableSetUpgradeable.Set",
            "members": [
              {
                "label": "_values",
                "type": "t_array(t_bytes32)dyn_storage"
              },
              {
                "label": "_indexes",
                "type": "t_mapping(t_bytes32,t_uint256)"
              }
            ]
          },
          "t_array(t_bytes32)dyn_storage": {
            "label": "bytes32[]"
          },
          "t_mapping(t_bytes32,t_uint256)": {
            "label": "mapping(bytes32 => uint256)"
          },
          "t_struct(UintToAddressMap)2221_storage": {
            "label": "struct EnumerableMapUpgradeable.UintToAddressMap",
            "members": [
              {
                "label": "_inner",
                "type": "t_struct(Map)1903_storage"
              }
            ]
          },
          "t_struct(Map)1903_storage": {
            "label": "struct EnumerableMapUpgradeable.Map",
            "members": [
              {
                "label": "_entries",
                "type": "t_array(t_struct(MapEntry)1895_storage)dyn_storage"
              },
              {
                "label": "_indexes",
                "type": "t_mapping(t_bytes32,t_uint256)"
              }
            ]
          },
          "t_array(t_struct(MapEntry)1895_storage)dyn_storage": {
            "label": "struct EnumerableMapUpgradeable.MapEntry[]"
          },
          "t_struct(MapEntry)1895_storage": {
            "label": "struct EnumerableMapUpgradeable.MapEntry",
            "members": [
              {
                "label": "_key",
                "type": "t_bytes32"
              },
              {
                "label": "_value",
                "type": "t_bytes32"
              }
            ]
          },
          "t_mapping(t_address,t_mapping(t_address,t_bool))": {
            "label": "mapping(address => mapping(address => bool))"
          },
          "t_string_storage": {
            "label": "string"
          },
          "t_mapping(t_uint256,t_string_storage)": {
            "label": "mapping(uint256 => string)"
          },
          "t_mapping(t_uint256,t_bool)": {
            "label": "mapping(uint256 => bool)"
          },
          "t_array(t_uint256)40_storage": {
            "label": "uint256[40]"
          },
          "t_mapping(t_bytes4,t_bool)": {
            "label": "mapping(bytes4 => bool)"
          },
          "t_bytes4": {
            "label": "bytes4"
          }
        }
      }
    },
    "b475f4f0e97a5212a17914e61230156fe7a0bd3ff818f9db9e94bd757c2dcd98": {
      "address": "0xf5c502A8c31A210EAB6b7837E7C56d65d3Af2F83",
      "txHash": "0xa4964cae383c0557561a923661efd318b0796b8fc51db0f52a486dc16a9dbcb9",
      "layout": {
        "storage": [
          {
            "contract": "Initializable",
            "label": "_initialized",
            "type": "t_bool",
            "src": "../@openzeppelin/contracts-upgradeable/proxy/Initializable.sol:25"
          },
          {
            "contract": "Initializable",
            "label": "_initializing",
            "type": "t_bool",
            "src": "../@openzeppelin/contracts-upgradeable/proxy/Initializable.sol:30"
          },
          {
            "contract": "ContextUpgradeable",
            "label": "__gap",
            "type": "t_array(t_uint256)50_storage",
            "src": "../@openzeppelin/contracts-upgradeable/utils/ContextUpgradeable.sol:31"
          },
          {
            "contract": "ERC165Upgradeable",
            "label": "_supportedInterfaces",
            "type": "t_mapping(t_bytes4,t_bool)",
            "src": "../@openzeppelin/contracts-upgradeable/introspection/ERC165Upgradeable.sol:23"
          },
          {
            "contract": "ERC165Upgradeable",
            "label": "__gap",
            "type": "t_array(t_uint256)49_storage",
            "src": "../@openzeppelin/contracts-upgradeable/introspection/ERC165Upgradeable.sol:59"
          },
          {
            "contract": "ERC721Upgradeable",
            "label": "_holderTokens",
            "type": "t_mapping(t_address,t_struct(UintSet)3148_storage)",
            "src": "../project:/contracts/ERC721Upgradeable.sol:34"
          },
          {
            "contract": "ERC721Upgradeable",
            "label": "_tokenOwners",
            "type": "t_struct(UintToAddressMap)2525_storage",
            "src": "../project:/contracts/ERC721Upgradeable.sol:37"
          },
          {
            "contract": "ERC721Upgradeable",
            "label": "_tokenApprovals",
            "type": "t_mapping(t_uint256,t_address)",
            "src": "../project:/contracts/ERC721Upgradeable.sol:40"
          },
          {
            "contract": "ERC721Upgradeable",
            "label": "_operatorApprovals",
            "type": "t_mapping(t_address,t_mapping(t_address,t_bool))",
            "src": "../project:/contracts/ERC721Upgradeable.sol:43"
          },
          {
            "contract": "ERC721Upgradeable",
            "label": "_name",
            "type": "t_string_storage",
            "src": "../project:/contracts/ERC721Upgradeable.sol:46"
          },
          {
            "contract": "ERC721Upgradeable",
            "label": "_symbol",
            "type": "t_string_storage",
            "src": "../project:/contracts/ERC721Upgradeable.sol:49"
          },
          {
            "contract": "ERC721Upgradeable",
            "label": "_tokenURIs",
            "type": "t_mapping(t_uint256,t_string_storage)",
            "src": "../project:/contracts/ERC721Upgradeable.sol:52"
          },
          {
            "contract": "ERC721Upgradeable",
            "label": "_baseURI",
            "type": "t_string_storage",
            "src": "../project:/contracts/ERC721Upgradeable.sol:55"
          },
          {
            "contract": "ERC721Upgradeable",
            "label": "_burnedTokens",
            "type": "t_mapping(t_uint256,t_bool)",
            "src": "../project:/contracts/ERC721Upgradeable.sol:92"
          },
          {
            "contract": "ERC721Upgradeable",
            "label": "__gap",
            "type": "t_array(t_uint256)40_storage",
            "src": "../project:/contracts/ERC721Upgradeable.sol:494"
          },
          {
            "contract": "ERC721DefaultApproval",
            "label": "defaultApprovals",
            "type": "t_mapping(t_address,t_bool)",
            "src": "../project:/contracts/ERC721DefaultApproval.sol:7"
          },
          {
            "contract": "ERC721DefaultApproval",
            "label": "__gap",
            "type": "t_array(t_uint256)50_storage",
            "src": "../project:/contracts/ERC721DefaultApproval.sol:23"
          },
          {
            "contract": "ERC721BurnableUpgradeable",
            "label": "__gap",
            "type": "t_array(t_uint256)50_storage",
            "src": "../project:/contracts/ERC721BurnableUpgradeable.sol:40"
          },
          {
            "contract": "EIP712Upgradeable",
            "label": "_HASHED_NAME",
            "type": "t_bytes32",
            "src": "../@openzeppelin/contracts-upgradeable/drafts/EIP712Upgradeable.sol:27"
          },
          {
            "contract": "EIP712Upgradeable",
            "label": "_HASHED_VERSION",
            "type": "t_bytes32",
            "src": "../@openzeppelin/contracts-upgradeable/drafts/EIP712Upgradeable.sol:28"
          },
          {
            "contract": "EIP712Upgradeable",
            "label": "__gap",
            "type": "t_array(t_uint256)50_storage",
            "src": "../@openzeppelin/contracts-upgradeable/drafts/EIP712Upgradeable.sol:120"
          },
          {
            "contract": "ERC1271ValidatorForERC721",
            "label": "__gap",
            "type": "t_array(t_uint256)50_storage",
            "src": "../project:/contracts/Mint721Validator.sol:26"
          },
          {
            "contract": "Mint721Validator",
            "label": "__gap",
            "type": "t_array(t_uint256)50_storage",
            "src": "../project:/contracts/Mint721Validator.sol:37"
          },
          {
            "contract": "OwnableUpgradeable",
            "label": "_owner",
            "type": "t_address",
            "src": "../@openzeppelin/contracts-upgradeable/access/OwnableUpgradeable.sol:20"
          },
          {
            "contract": "OwnableUpgradeable",
            "label": "__gap",
            "type": "t_array(t_uint256)49_storage",
            "src": "../@openzeppelin/contracts-upgradeable/access/OwnableUpgradeable.sol:74"
          },
          {
            "contract": "ERC721Lazy",
            "label": "creators",
            "type": "t_mapping(t_uint256,t_address)",
            "src": "../project:/contracts/ERC721Lazy.sol:21"
          },
          {
            "contract": "ERC721Lazy",
            "label": "royaltyFees",
            "type": "t_mapping(t_uint256,t_uint256)",
            "src": "../project:/contracts/ERC721Lazy.sol:22"
          },
          {
            "contract": "ERC721Lazy",
            "label": "metasaltToken",
            "type": "t_address",
            "src": "../project:/contracts/ERC721Lazy.sol:23"
          },
          {
            "contract": "ERC721Lazy",
            "label": "MetasaltTokenCreateRewardValue",
            "type": "t_uint256",
            "src": "../project:/contracts/ERC721Lazy.sol:24"
          },
          {
            "contract": "ERC721Lazy",
            "label": "__gap",
            "type": "t_array(t_uint256)50_storage",
            "src": "../project:/contracts/ERC721Lazy.sol:121"
          },
          {
            "contract": "ERC721Base",
            "label": "__gap",
            "type": "t_array(t_uint256)50_storage",
            "src": "../project:/contracts/ERC721Base.sol:26"
          },
          {
            "contract": "ERC721MetaSalt",
            "label": "__gap",
            "type": "t_array(t_uint256)50_storage",
            "src": "../project:/contracts/ERC721MetaSalt.sol:25"
          }
        ],
        "types": {
          "t_array(t_uint256)50_storage": {
            "label": "uint256[50]"
          },
          "t_uint256": {
            "label": "uint256"
          },
          "t_mapping(t_uint256,t_address)": {
            "label": "mapping(uint256 => address)"
          },
          "t_address": {
            "label": "address"
          },
          "t_mapping(t_uint256,t_uint256)": {
            "label": "mapping(uint256 => uint256)"
          },
          "t_array(t_uint256)49_storage": {
            "label": "uint256[49]"
          },
          "t_bytes32": {
            "label": "bytes32"
          },
          "t_mapping(t_address,t_bool)": {
            "label": "mapping(address => bool)"
          },
          "t_bool": {
            "label": "bool"
          },
          "t_mapping(t_address,t_struct(UintSet)3148_storage)": {
            "label": "mapping(address => struct EnumerableSetUpgradeable.UintSet)"
          },
          "t_struct(UintSet)3148_storage": {
            "label": "struct EnumerableSetUpgradeable.UintSet",
            "members": [
              {
                "label": "_inner",
                "type": "t_struct(Set)2762_storage"
              }
            ]
          },
          "t_struct(Set)2762_storage": {
            "label": "struct EnumerableSetUpgradeable.Set",
            "members": [
              {
                "label": "_values",
                "type": "t_array(t_bytes32)dyn_storage"
              },
              {
                "label": "_indexes",
                "type": "t_mapping(t_bytes32,t_uint256)"
              }
            ]
          },
          "t_array(t_bytes32)dyn_storage": {
            "label": "bytes32[]"
          },
          "t_mapping(t_bytes32,t_uint256)": {
            "label": "mapping(bytes32 => uint256)"
          },
          "t_struct(UintToAddressMap)2525_storage": {
            "label": "struct EnumerableMapUpgradeable.UintToAddressMap",
            "members": [
              {
                "label": "_inner",
                "type": "t_struct(Map)2207_storage"
              }
            ]
          },
          "t_struct(Map)2207_storage": {
            "label": "struct EnumerableMapUpgradeable.Map",
            "members": [
              {
                "label": "_entries",
                "type": "t_array(t_struct(MapEntry)2199_storage)dyn_storage"
              },
              {
                "label": "_indexes",
                "type": "t_mapping(t_bytes32,t_uint256)"
              }
            ]
          },
          "t_array(t_struct(MapEntry)2199_storage)dyn_storage": {
            "label": "struct EnumerableMapUpgradeable.MapEntry[]"
          },
          "t_struct(MapEntry)2199_storage": {
            "label": "struct EnumerableMapUpgradeable.MapEntry",
            "members": [
              {
                "label": "_key",
                "type": "t_bytes32"
              },
              {
                "label": "_value",
                "type": "t_bytes32"
              }
            ]
          },
          "t_mapping(t_address,t_mapping(t_address,t_bool))": {
            "label": "mapping(address => mapping(address => bool))"
          },
          "t_string_storage": {
            "label": "string"
          },
          "t_mapping(t_uint256,t_string_storage)": {
            "label": "mapping(uint256 => string)"
          },
          "t_mapping(t_uint256,t_bool)": {
            "label": "mapping(uint256 => bool)"
          },
          "t_array(t_uint256)40_storage": {
            "label": "uint256[40]"
          },
          "t_mapping(t_bytes4,t_bool)": {
            "label": "mapping(bytes4 => bool)"
          },
          "t_bytes4": {
            "label": "bytes4"
          }
        }
      }
    },
    "7a7fb2cfed15eeadc3b4334dc9c280468abd2c6803f9725d8f6905ea0a545d59": {
      "address": "0xf8f3bc18bee85D3459ca2dB6505C599F60939e62",
      "txHash": "0x9677bf6b684241e0cf36b3fa454a2a1690dab1d1d811c8d6ed901c5c0a9b6b02",
      "layout": {
        "storage": [
          {
            "contract": "Initializable",
            "label": "_initialized",
            "type": "t_bool",
            "src": "../@openzeppelin/contracts-upgradeable/proxy/Initializable.sol:25"
          },
          {
            "contract": "Initializable",
            "label": "_initializing",
            "type": "t_bool",
            "src": "../@openzeppelin/contracts-upgradeable/proxy/Initializable.sol:30"
          },
          {
            "contract": "ContextUpgradeable",
            "label": "__gap",
            "type": "t_array(t_uint256)50_storage",
            "src": "../@openzeppelin/contracts-upgradeable/utils/ContextUpgradeable.sol:31"
          },
          {
            "contract": "ERC165Upgradeable",
            "label": "_supportedInterfaces",
            "type": "t_mapping(t_bytes4,t_bool)",
            "src": "../@openzeppelin/contracts-upgradeable/introspection/ERC165Upgradeable.sol:23"
          },
          {
            "contract": "ERC165Upgradeable",
            "label": "__gap",
            "type": "t_array(t_uint256)49_storage",
            "src": "../@openzeppelin/contracts-upgradeable/introspection/ERC165Upgradeable.sol:59"
          },
          {
            "contract": "ERC1155Upgradeable",
            "label": "_balances",
            "type": "t_mapping(t_uint256,t_mapping(t_address,t_uint256))",
            "src": "../project:/contracts/erc-1155/ERC1155Upgradeable.sol:27"
          },
          {
            "contract": "ERC1155Upgradeable",
            "label": "_operatorApprovals",
            "type": "t_mapping(t_address,t_mapping(t_address,t_bool))",
            "src": "../project:/contracts/erc-1155/ERC1155Upgradeable.sol:30"
          },
          {
            "contract": "ERC1155Upgradeable",
            "label": "_uri",
            "type": "t_string_storage",
            "src": "../project:/contracts/erc-1155/ERC1155Upgradeable.sol:33"
          },
          {
            "contract": "ERC1155Upgradeable",
            "label": "__gap",
            "type": "t_array(t_uint256)47_storage",
            "src": "../project:/contracts/erc-1155/ERC1155Upgradeable.sol:421"
          },
          {
            "contract": "ERC1155BaseURI",
            "label": "_tokenURIs",
            "type": "t_mapping(t_uint256,t_string_storage)",
            "src": "../project:/contracts/erc-1155/ERC1155BaseURI.sol:14"
          },
          {
            "contract": "ERC1155BaseURI",
            "label": "_baseURI",
            "type": "t_string_storage",
            "src": "../project:/contracts/erc-1155/ERC1155BaseURI.sol:17"
          },
          {
            "contract": "ERC1155BaseURI",
            "label": "__gap",
            "type": "t_array(t_uint256)50_storage",
            "src": "../project:/contracts/erc-1155/ERC1155BaseURI.sol:69"
          },
          {
            "contract": "EIP712Upgradeable",
            "label": "_HASHED_NAME",
            "type": "t_bytes32",
            "src": "../@openzeppelin/contracts-upgradeable/drafts/EIP712Upgradeable.sol:27"
          },
          {
            "contract": "EIP712Upgradeable",
            "label": "_HASHED_VERSION",
            "type": "t_bytes32",
            "src": "../@openzeppelin/contracts-upgradeable/drafts/EIP712Upgradeable.sol:28"
          },
          {
            "contract": "EIP712Upgradeable",
            "label": "__gap",
            "type": "t_array(t_uint256)50_storage",
            "src": "../@openzeppelin/contracts-upgradeable/drafts/EIP712Upgradeable.sol:120"
          },
          {
            "contract": "ERC1271Validator",
            "label": "__gap",
            "type": "t_array(t_uint256)50_storage",
            "src": "../project:/contracts/erc-1271/ERC1271Validator.sol:25"
          },
          {
            "contract": "Mint1155Validator",
            "label": "__gap",
            "type": "t_array(t_uint256)50_storage",
            "src": "../project:/contracts/erc-1155/Mint1155Validator.sol:16"
          },
          {
            "contract": "OwnableUpgradeable",
            "label": "_owner",
            "type": "t_address",
            "src": "../@openzeppelin/contracts-upgradeable/access/OwnableUpgradeable.sol:20"
          },
          {
            "contract": "OwnableUpgradeable",
            "label": "__gap",
            "type": "t_array(t_uint256)49_storage",
            "src": "../@openzeppelin/contracts-upgradeable/access/OwnableUpgradeable.sol:74"
          },
          {
            "contract": "ERC1155DefaultApproval",
            "label": "defaultApprovals",
            "type": "t_mapping(t_address,t_bool)",
            "src": "../project:/contracts/erc-1155/ERC1155DefaultApproval.sol:8"
          },
          {
            "contract": "ERC1155DefaultApproval",
            "label": "__gap",
            "type": "t_array(t_uint256)50_storage",
            "src": "../project:/contracts/erc-1155/ERC1155DefaultApproval.sol:20"
          },
          {
            "contract": "ERC1155BurnableUpgradeable",
            "label": "__gap",
            "type": "t_array(t_uint256)50_storage",
            "src": "../project:/contracts/erc-1155/ERC1155BurnableUpgradeable.sol:41"
          },
          {
            "contract": "ERC1155Lazy",
            "label": "creators",
            "type": "t_mapping(t_uint256,t_address)",
            "src": "../project:/contracts/erc-1155/ERC1155Lazy.sol:20"
          },
          {
            "contract": "ERC1155Lazy",
            "label": "royaltyFees",
            "type": "t_mapping(t_uint256,t_uint256)",
            "src": "../project:/contracts/erc-1155/ERC1155Lazy.sol:21"
          },
          {
            "contract": "ERC1155Lazy",
            "label": "supply",
            "type": "t_mapping(t_uint256,t_uint256)",
            "src": "../project:/contracts/erc-1155/ERC1155Lazy.sol:22"
          },
          {
            "contract": "ERC1155Lazy",
            "label": "minted",
            "type": "t_mapping(t_uint256,t_uint256)",
            "src": "../project:/contracts/erc-1155/ERC1155Lazy.sol:23"
          },
          {
            "contract": "ERC1155Lazy",
            "label": "metasaltToken",
            "type": "t_address",
            "src": "../project:/contracts/erc-1155/ERC1155Lazy.sol:24"
          },
          {
            "contract": "ERC1155Lazy",
            "label": "MetasaltTokenCreateRewardValue",
            "type": "t_uint256",
            "src": "../project:/contracts/erc-1155/ERC1155Lazy.sol:25"
          },
          {
            "contract": "ERC1155Lazy",
            "label": "__gap",
            "type": "t_array(t_uint256)50_storage",
            "src": "../project:/contracts/erc-1155/ERC1155Lazy.sol:177"
          },
          {
            "contract": "ERC1155Base",
            "label": "name",
            "type": "t_string_storage",
            "src": "../project:/contracts/erc-1155/ERC1155Base.sol:12"
          },
          {
            "contract": "ERC1155Base",
            "label": "symbol",
            "type": "t_string_storage",
            "src": "../project:/contracts/erc-1155/ERC1155Base.sol:13"
          },
          {
            "contract": "ERC1155Base",
            "label": "__gap",
            "type": "t_array(t_uint256)50_storage",
            "src": "../project:/contracts/erc-1155/ERC1155Base.sol:81"
          },
          {
            "contract": "ERC1155MetaSalt",
            "label": "__gap",
            "type": "t_array(t_uint256)49_storage",
            "src": "../project:/contracts/erc-1155/ERC1155MetaSalt.sol:24"
          }
        ],
        "types": {
          "t_array(t_uint256)49_storage": {
            "label": "uint256[49]"
          },
          "t_uint256": {
            "label": "uint256"
          },
          "t_string_storage": {
            "label": "string"
          },
          "t_array(t_uint256)50_storage": {
            "label": "uint256[50]"
          },
          "t_mapping(t_uint256,t_address)": {
            "label": "mapping(uint256 => address)"
          },
          "t_address": {
            "label": "address"
          },
          "t_mapping(t_uint256,t_uint256)": {
            "label": "mapping(uint256 => uint256)"
          },
          "t_mapping(t_address,t_bool)": {
            "label": "mapping(address => bool)"
          },
          "t_bool": {
            "label": "bool"
          },
          "t_bytes32": {
            "label": "bytes32"
          },
          "t_mapping(t_uint256,t_string_storage)": {
            "label": "mapping(uint256 => string)"
          },
          "t_mapping(t_uint256,t_mapping(t_address,t_uint256))": {
            "label": "mapping(uint256 => mapping(address => uint256))"
          },
          "t_mapping(t_address,t_uint256)": {
            "label": "mapping(address => uint256)"
          },
          "t_mapping(t_address,t_mapping(t_address,t_bool))": {
            "label": "mapping(address => mapping(address => bool))"
          },
          "t_array(t_uint256)47_storage": {
            "label": "uint256[47]"
          },
          "t_mapping(t_bytes4,t_bool)": {
            "label": "mapping(bytes4 => bool)"
          },
          "t_bytes4": {
            "label": "bytes4"
          }
        }
      }
    },
    "9e46ed548c03dc469c9e447b9507608028db694cd859a665ee817066101c99fb": {
      "address": "0x883804e033e5ce06FEcfeb3D572F40E6737615C8",
      "txHash": "0x3086b2e26939cccdebed36db502f6d1a4b23d298ad94beb5fb50b24ac334b162",
      "layout": {
        "storage": [
          {
            "contract": "Initializable",
            "label": "_initialized",
            "type": "t_bool",
            "src": "../@openzeppelin/contracts-upgradeable/proxy/Initializable.sol:25"
          },
          {
            "contract": "Initializable",
            "label": "_initializing",
            "type": "t_bool",
            "src": "../@openzeppelin/contracts-upgradeable/proxy/Initializable.sol:30"
          },
          {
            "contract": "ContextUpgradeable",
            "label": "__gap",
            "type": "t_array(t_uint256)50_storage",
            "src": "../@openzeppelin/contracts-upgradeable/utils/ContextUpgradeable.sol:31"
          },
          {
            "contract": "ERC165Upgradeable",
            "label": "_supportedInterfaces",
            "type": "t_mapping(t_bytes4,t_bool)",
            "src": "../@openzeppelin/contracts-upgradeable/introspection/ERC165Upgradeable.sol:23"
          },
          {
            "contract": "ERC165Upgradeable",
            "label": "__gap",
            "type": "t_array(t_uint256)49_storage",
            "src": "../@openzeppelin/contracts-upgradeable/introspection/ERC165Upgradeable.sol:59"
          },
          {
            "contract": "ERC1155Upgradeable",
            "label": "_balances",
            "type": "t_mapping(t_uint256,t_mapping(t_address,t_uint256))",
            "src": "../project:/contracts/erc-1155/ERC1155Upgradeable.sol:27"
          },
          {
            "contract": "ERC1155Upgradeable",
            "label": "_operatorApprovals",
            "type": "t_mapping(t_address,t_mapping(t_address,t_bool))",
            "src": "../project:/contracts/erc-1155/ERC1155Upgradeable.sol:30"
          },
          {
            "contract": "ERC1155Upgradeable",
            "label": "_uri",
            "type": "t_string_storage",
            "src": "../project:/contracts/erc-1155/ERC1155Upgradeable.sol:33"
          },
          {
            "contract": "ERC1155Upgradeable",
            "label": "__gap",
            "type": "t_array(t_uint256)47_storage",
            "src": "../project:/contracts/erc-1155/ERC1155Upgradeable.sol:421"
          },
          {
            "contract": "ERC1155BaseURI",
            "label": "_tokenURIs",
            "type": "t_mapping(t_uint256,t_string_storage)",
            "src": "../project:/contracts/erc-1155/ERC1155BaseURI.sol:14"
          },
          {
            "contract": "ERC1155BaseURI",
            "label": "_baseURI",
            "type": "t_string_storage",
            "src": "../project:/contracts/erc-1155/ERC1155BaseURI.sol:17"
          },
          {
            "contract": "ERC1155BaseURI",
            "label": "__gap",
            "type": "t_array(t_uint256)50_storage",
            "src": "../project:/contracts/erc-1155/ERC1155BaseURI.sol:69"
          },
          {
            "contract": "EIP712Upgradeable",
            "label": "_HASHED_NAME",
            "type": "t_bytes32",
            "src": "../@openzeppelin/contracts-upgradeable/drafts/EIP712Upgradeable.sol:27"
          },
          {
            "contract": "EIP712Upgradeable",
            "label": "_HASHED_VERSION",
            "type": "t_bytes32",
            "src": "../@openzeppelin/contracts-upgradeable/drafts/EIP712Upgradeable.sol:28"
          },
          {
            "contract": "EIP712Upgradeable",
            "label": "__gap",
            "type": "t_array(t_uint256)50_storage",
            "src": "../@openzeppelin/contracts-upgradeable/drafts/EIP712Upgradeable.sol:120"
          },
          {
            "contract": "ERC1271Validator",
            "label": "__gap",
            "type": "t_array(t_uint256)50_storage",
            "src": "../project:/contracts/erc-1271/ERC1271Validator.sol:25"
          },
          {
            "contract": "Mint1155Validator",
            "label": "__gap",
            "type": "t_array(t_uint256)50_storage",
            "src": "../project:/contracts/erc-1155/Mint1155Validator.sol:16"
          },
          {
            "contract": "OwnableUpgradeable",
            "label": "_owner",
            "type": "t_address",
            "src": "../@openzeppelin/contracts-upgradeable/access/OwnableUpgradeable.sol:20"
          },
          {
            "contract": "OwnableUpgradeable",
            "label": "__gap",
            "type": "t_array(t_uint256)49_storage",
            "src": "../@openzeppelin/contracts-upgradeable/access/OwnableUpgradeable.sol:74"
          },
          {
            "contract": "ERC1155DefaultApproval",
            "label": "defaultApprovals",
            "type": "t_mapping(t_address,t_bool)",
            "src": "../project:/contracts/erc-1155/ERC1155DefaultApproval.sol:8"
          },
          {
            "contract": "ERC1155DefaultApproval",
            "label": "__gap",
            "type": "t_array(t_uint256)50_storage",
            "src": "../project:/contracts/erc-1155/ERC1155DefaultApproval.sol:20"
          },
          {
            "contract": "ERC1155BurnableUpgradeable",
            "label": "__gap",
            "type": "t_array(t_uint256)50_storage",
            "src": "../project:/contracts/erc-1155/ERC1155BurnableUpgradeable.sol:41"
          },
          {
            "contract": "ERC1155Lazy",
            "label": "creators",
            "type": "t_mapping(t_uint256,t_address)",
            "src": "../project:/contracts/erc-1155/ERC1155Lazy.sol:20"
          },
          {
            "contract": "ERC1155Lazy",
            "label": "royaltyFees",
            "type": "t_mapping(t_uint256,t_uint256)",
            "src": "../project:/contracts/erc-1155/ERC1155Lazy.sol:21"
          },
          {
            "contract": "ERC1155Lazy",
            "label": "supply",
            "type": "t_mapping(t_uint256,t_uint256)",
            "src": "../project:/contracts/erc-1155/ERC1155Lazy.sol:22"
          },
          {
            "contract": "ERC1155Lazy",
            "label": "minted",
            "type": "t_mapping(t_uint256,t_uint256)",
            "src": "../project:/contracts/erc-1155/ERC1155Lazy.sol:23"
          },
          {
            "contract": "ERC1155Lazy",
            "label": "metasaltToken",
            "type": "t_address",
            "src": "../project:/contracts/erc-1155/ERC1155Lazy.sol:24"
          },
          {
            "contract": "ERC1155Lazy",
            "label": "MetasaltTokenCreateRewardValue",
            "type": "t_uint256",
            "src": "../project:/contracts/erc-1155/ERC1155Lazy.sol:25"
          },
          {
            "contract": "ERC1155Lazy",
            "label": "__gap",
            "type": "t_array(t_uint256)50_storage",
            "src": "../project:/contracts/erc-1155/ERC1155Lazy.sol:177"
          },
          {
            "contract": "ERC1155Base",
            "label": "name",
            "type": "t_string_storage",
            "src": "../project:/contracts/erc-1155/ERC1155Base.sol:12"
          },
          {
            "contract": "ERC1155Base",
            "label": "symbol",
            "type": "t_string_storage",
            "src": "../project:/contracts/erc-1155/ERC1155Base.sol:13"
          },
          {
            "contract": "ERC1155Base",
            "label": "__gap",
            "type": "t_array(t_uint256)50_storage",
            "src": "../project:/contracts/erc-1155/ERC1155Base.sol:81"
          },
          {
            "contract": "ERC1155MetaSalt",
            "label": "__gap",
            "type": "t_array(t_uint256)49_storage",
            "src": "../project:/contracts/erc-1155/ERC1155MetaSalt.sol:24"
          }
        ],
        "types": {
          "t_array(t_uint256)49_storage": {
            "label": "uint256[49]"
          },
          "t_uint256": {
            "label": "uint256"
          },
          "t_string_storage": {
            "label": "string"
          },
          "t_array(t_uint256)50_storage": {
            "label": "uint256[50]"
          },
          "t_mapping(t_uint256,t_address)": {
            "label": "mapping(uint256 => address)"
          },
          "t_address": {
            "label": "address"
          },
          "t_mapping(t_uint256,t_uint256)": {
            "label": "mapping(uint256 => uint256)"
          },
          "t_mapping(t_address,t_bool)": {
            "label": "mapping(address => bool)"
          },
          "t_bool": {
            "label": "bool"
          },
          "t_bytes32": {
            "label": "bytes32"
          },
          "t_mapping(t_uint256,t_string_storage)": {
            "label": "mapping(uint256 => string)"
          },
          "t_mapping(t_uint256,t_mapping(t_address,t_uint256))": {
            "label": "mapping(uint256 => mapping(address => uint256))"
          },
          "t_mapping(t_address,t_uint256)": {
            "label": "mapping(address => uint256)"
          },
          "t_mapping(t_address,t_mapping(t_address,t_bool))": {
            "label": "mapping(address => mapping(address => bool))"
          },
          "t_array(t_uint256)47_storage": {
            "label": "uint256[47]"
          },
          "t_mapping(t_bytes4,t_bool)": {
            "label": "mapping(bytes4 => bool)"
          },
          "t_bytes4": {
            "label": "bytes4"
          }
        }
      }
    },
    "533cfcab92b2d51b8154e20263ed95ec33c1ec89c874b449f519eee5f200cb7c": {
      "address": "0x3f8a1A79d0633936Be5b0c357896F403Ead8761f",
      "txHash": "0x4a630738f59fdaca5335817fc1bb9f4aba5385730ccb38c01038be2da7f8c30b",
      "layout": {
        "storage": [
          {
            "contract": "Initializable",
            "label": "_initialized",
            "type": "t_bool",
            "src": "../@openzeppelin/contracts-upgradeable/proxy/Initializable.sol:25"
          },
          {
            "contract": "Initializable",
            "label": "_initializing",
            "type": "t_bool",
            "src": "../@openzeppelin/contracts-upgradeable/proxy/Initializable.sol:30"
          },
          {
            "contract": "ContextUpgradeable",
            "label": "__gap",
            "type": "t_array(t_uint256)50_storage",
            "src": "../@openzeppelin/contracts-upgradeable/utils/ContextUpgradeable.sol:31"
          },
          {
            "contract": "ERC165Upgradeable",
            "label": "_supportedInterfaces",
            "type": "t_mapping(t_bytes4,t_bool)",
            "src": "../@openzeppelin/contracts-upgradeable/introspection/ERC165Upgradeable.sol:23"
          },
          {
            "contract": "ERC165Upgradeable",
            "label": "__gap",
            "type": "t_array(t_uint256)49_storage",
            "src": "../@openzeppelin/contracts-upgradeable/introspection/ERC165Upgradeable.sol:59"
          },
          {
            "contract": "ERC721Upgradeable",
            "label": "_holderTokens",
            "type": "t_mapping(t_address,t_struct(UintSet)3148_storage)",
            "src": "../project:/contracts/ERC721Upgradeable.sol:34"
          },
          {
            "contract": "ERC721Upgradeable",
            "label": "_tokenOwners",
            "type": "t_struct(UintToAddressMap)2525_storage",
            "src": "../project:/contracts/ERC721Upgradeable.sol:37"
          },
          {
            "contract": "ERC721Upgradeable",
            "label": "_tokenApprovals",
            "type": "t_mapping(t_uint256,t_address)",
            "src": "../project:/contracts/ERC721Upgradeable.sol:40"
          },
          {
            "contract": "ERC721Upgradeable",
            "label": "_operatorApprovals",
            "type": "t_mapping(t_address,t_mapping(t_address,t_bool))",
            "src": "../project:/contracts/ERC721Upgradeable.sol:43"
          },
          {
            "contract": "ERC721Upgradeable",
            "label": "_name",
            "type": "t_string_storage",
            "src": "../project:/contracts/ERC721Upgradeable.sol:46"
          },
          {
            "contract": "ERC721Upgradeable",
            "label": "_symbol",
            "type": "t_string_storage",
            "src": "../project:/contracts/ERC721Upgradeable.sol:49"
          },
          {
            "contract": "ERC721Upgradeable",
            "label": "_tokenURIs",
            "type": "t_mapping(t_uint256,t_string_storage)",
            "src": "../project:/contracts/ERC721Upgradeable.sol:52"
          },
          {
            "contract": "ERC721Upgradeable",
            "label": "_baseURI",
            "type": "t_string_storage",
            "src": "../project:/contracts/ERC721Upgradeable.sol:55"
          },
          {
            "contract": "ERC721Upgradeable",
            "label": "_burnedTokens",
            "type": "t_mapping(t_uint256,t_bool)",
            "src": "../project:/contracts/ERC721Upgradeable.sol:92"
          },
          {
            "contract": "ERC721Upgradeable",
            "label": "__gap",
            "type": "t_array(t_uint256)40_storage",
            "src": "../project:/contracts/ERC721Upgradeable.sol:494"
          },
          {
            "contract": "ERC721DefaultApproval",
            "label": "defaultApprovals",
            "type": "t_mapping(t_address,t_bool)",
            "src": "../project:/contracts/ERC721DefaultApproval.sol:7"
          },
          {
            "contract": "ERC721DefaultApproval",
            "label": "__gap",
            "type": "t_array(t_uint256)50_storage",
            "src": "../project:/contracts/ERC721DefaultApproval.sol:23"
          },
          {
            "contract": "ERC721BurnableUpgradeable",
            "label": "__gap",
            "type": "t_array(t_uint256)50_storage",
            "src": "../project:/contracts/ERC721BurnableUpgradeable.sol:40"
          },
          {
            "contract": "EIP712Upgradeable",
            "label": "_HASHED_NAME",
            "type": "t_bytes32",
            "src": "../@openzeppelin/contracts-upgradeable/drafts/EIP712Upgradeable.sol:27"
          },
          {
            "contract": "EIP712Upgradeable",
            "label": "_HASHED_VERSION",
            "type": "t_bytes32",
            "src": "../@openzeppelin/contracts-upgradeable/drafts/EIP712Upgradeable.sol:28"
          },
          {
            "contract": "EIP712Upgradeable",
            "label": "__gap",
            "type": "t_array(t_uint256)50_storage",
            "src": "../@openzeppelin/contracts-upgradeable/drafts/EIP712Upgradeable.sol:120"
          },
          {
            "contract": "ERC1271ValidatorForERC721",
            "label": "__gap",
            "type": "t_array(t_uint256)50_storage",
            "src": "../project:/contracts/Mint721Validator.sol:26"
          },
          {
            "contract": "Mint721Validator",
            "label": "__gap",
            "type": "t_array(t_uint256)50_storage",
            "src": "../project:/contracts/Mint721Validator.sol:37"
          },
          {
            "contract": "OwnableUpgradeable",
            "label": "_owner",
            "type": "t_address",
            "src": "../@openzeppelin/contracts-upgradeable/access/OwnableUpgradeable.sol:20"
          },
          {
            "contract": "OwnableUpgradeable",
            "label": "__gap",
            "type": "t_array(t_uint256)49_storage",
            "src": "../@openzeppelin/contracts-upgradeable/access/OwnableUpgradeable.sol:74"
          },
          {
            "contract": "ERC721Lazy",
            "label": "creators",
            "type": "t_mapping(t_uint256,t_address)",
            "src": "../project:/contracts/ERC721Lazy.sol:21"
          },
          {
            "contract": "ERC721Lazy",
            "label": "royaltyFees",
            "type": "t_mapping(t_uint256,t_uint256)",
            "src": "../project:/contracts/ERC721Lazy.sol:22"
          },
          {
            "contract": "ERC721Lazy",
            "label": "metasaltToken",
            "type": "t_address",
            "src": "../project:/contracts/ERC721Lazy.sol:23"
          },
          {
            "contract": "ERC721Lazy",
            "label": "MetasaltTokenCreateRewardValue",
            "type": "t_uint256",
            "src": "../project:/contracts/ERC721Lazy.sol:24"
          },
          {
            "contract": "ERC721Lazy",
            "label": "__gap",
            "type": "t_array(t_uint256)50_storage",
            "src": "../project:/contracts/ERC721Lazy.sol:121"
          },
          {
            "contract": "ERC721Base",
            "label": "__gap",
            "type": "t_array(t_uint256)50_storage",
            "src": "../project:/contracts/ERC721Base.sol:26"
          },
          {
            "contract": "ERC721MetaSalt",
            "label": "__gap",
            "type": "t_array(t_uint256)50_storage",
            "src": "../project:/contracts/ERC721MetaSalt.sol:25"
          }
        ],
        "types": {
          "t_array(t_uint256)50_storage": {
            "label": "uint256[50]"
          },
          "t_uint256": {
            "label": "uint256"
          },
          "t_mapping(t_uint256,t_address)": {
            "label": "mapping(uint256 => address)"
          },
          "t_address": {
            "label": "address"
          },
          "t_mapping(t_uint256,t_uint256)": {
            "label": "mapping(uint256 => uint256)"
          },
          "t_array(t_uint256)49_storage": {
            "label": "uint256[49]"
          },
          "t_bytes32": {
            "label": "bytes32"
          },
          "t_mapping(t_address,t_bool)": {
            "label": "mapping(address => bool)"
          },
          "t_bool": {
            "label": "bool"
          },
          "t_mapping(t_address,t_struct(UintSet)3148_storage)": {
            "label": "mapping(address => struct EnumerableSetUpgradeable.UintSet)"
          },
          "t_struct(UintSet)3148_storage": {
            "label": "struct EnumerableSetUpgradeable.UintSet",
            "members": [
              {
                "label": "_inner",
                "type": "t_struct(Set)2762_storage"
              }
            ]
          },
          "t_struct(Set)2762_storage": {
            "label": "struct EnumerableSetUpgradeable.Set",
            "members": [
              {
                "label": "_values",
                "type": "t_array(t_bytes32)dyn_storage"
              },
              {
                "label": "_indexes",
                "type": "t_mapping(t_bytes32,t_uint256)"
              }
            ]
          },
          "t_array(t_bytes32)dyn_storage": {
            "label": "bytes32[]"
          },
          "t_mapping(t_bytes32,t_uint256)": {
            "label": "mapping(bytes32 => uint256)"
          },
          "t_struct(UintToAddressMap)2525_storage": {
            "label": "struct EnumerableMapUpgradeable.UintToAddressMap",
            "members": [
              {
                "label": "_inner",
                "type": "t_struct(Map)2207_storage"
              }
            ]
          },
          "t_struct(Map)2207_storage": {
            "label": "struct EnumerableMapUpgradeable.Map",
            "members": [
              {
                "label": "_entries",
                "type": "t_array(t_struct(MapEntry)2199_storage)dyn_storage"
              },
              {
                "label": "_indexes",
                "type": "t_mapping(t_bytes32,t_uint256)"
              }
            ]
          },
          "t_array(t_struct(MapEntry)2199_storage)dyn_storage": {
            "label": "struct EnumerableMapUpgradeable.MapEntry[]"
          },
          "t_struct(MapEntry)2199_storage": {
            "label": "struct EnumerableMapUpgradeable.MapEntry",
            "members": [
              {
                "label": "_key",
                "type": "t_bytes32"
              },
              {
                "label": "_value",
                "type": "t_bytes32"
              }
            ]
          },
          "t_mapping(t_address,t_mapping(t_address,t_bool))": {
            "label": "mapping(address => mapping(address => bool))"
          },
          "t_string_storage": {
            "label": "string"
          },
          "t_mapping(t_uint256,t_string_storage)": {
            "label": "mapping(uint256 => string)"
          },
          "t_mapping(t_uint256,t_bool)": {
            "label": "mapping(uint256 => bool)"
          },
          "t_array(t_uint256)40_storage": {
            "label": "uint256[40]"
          },
          "t_mapping(t_bytes4,t_bool)": {
            "label": "mapping(bytes4 => bool)"
          },
          "t_bytes4": {
            "label": "bytes4"
          }
        }
      }
    },
    "4e89de7d417b67f0e368c9af3e976deedc91d448979e7726d38108ab95e09d49": {
      "address": "0x188274088225168faC1f65DDeCB24AC324572b04",
      "txHash": "0x542bfb8c573040ea27d6de3d6044608ee56c73f3c3da37d527946c1b9558f1f9",
      "layout": {
        "storage": [
          {
            "contract": "Initializable",
            "label": "_initialized",
            "type": "t_bool",
            "src": "../@openzeppelin/contracts-upgradeable/proxy/Initializable.sol:25"
          },
          {
            "contract": "Initializable",
            "label": "_initializing",
            "type": "t_bool",
            "src": "../@openzeppelin/contracts-upgradeable/proxy/Initializable.sol:30"
          },
          {
            "contract": "ContextUpgradeable",
            "label": "__gap",
            "type": "t_array(t_uint256)50_storage",
            "src": "../@openzeppelin/contracts-upgradeable/utils/ContextUpgradeable.sol:31"
          },
          {
            "contract": "ERC165Upgradeable",
            "label": "_supportedInterfaces",
            "type": "t_mapping(t_bytes4,t_bool)",
            "src": "../@openzeppelin/contracts-upgradeable/introspection/ERC165Upgradeable.sol:23"
          },
          {
            "contract": "ERC165Upgradeable",
            "label": "__gap",
            "type": "t_array(t_uint256)49_storage",
            "src": "../@openzeppelin/contracts-upgradeable/introspection/ERC165Upgradeable.sol:59"
          },
          {
            "contract": "ERC721Upgradeable",
            "label": "_holderTokens",
            "type": "t_mapping(t_address,t_struct(UintSet)3148_storage)",
            "src": "../project:/contracts/ERC721Upgradeable.sol:34"
          },
          {
            "contract": "ERC721Upgradeable",
            "label": "_tokenOwners",
            "type": "t_struct(UintToAddressMap)2525_storage",
            "src": "../project:/contracts/ERC721Upgradeable.sol:37"
          },
          {
            "contract": "ERC721Upgradeable",
            "label": "_tokenApprovals",
            "type": "t_mapping(t_uint256,t_address)",
            "src": "../project:/contracts/ERC721Upgradeable.sol:40"
          },
          {
            "contract": "ERC721Upgradeable",
            "label": "_operatorApprovals",
            "type": "t_mapping(t_address,t_mapping(t_address,t_bool))",
            "src": "../project:/contracts/ERC721Upgradeable.sol:43"
          },
          {
            "contract": "ERC721Upgradeable",
            "label": "_name",
            "type": "t_string_storage",
            "src": "../project:/contracts/ERC721Upgradeable.sol:46"
          },
          {
            "contract": "ERC721Upgradeable",
            "label": "_symbol",
            "type": "t_string_storage",
            "src": "../project:/contracts/ERC721Upgradeable.sol:49"
          },
          {
            "contract": "ERC721Upgradeable",
            "label": "_tokenURIs",
            "type": "t_mapping(t_uint256,t_string_storage)",
            "src": "../project:/contracts/ERC721Upgradeable.sol:52"
          },
          {
            "contract": "ERC721Upgradeable",
            "label": "_baseURI",
            "type": "t_string_storage",
            "src": "../project:/contracts/ERC721Upgradeable.sol:55"
          },
          {
            "contract": "ERC721Upgradeable",
            "label": "_burnedTokens",
            "type": "t_mapping(t_uint256,t_bool)",
            "src": "../project:/contracts/ERC721Upgradeable.sol:92"
          },
          {
            "contract": "ERC721Upgradeable",
            "label": "__gap",
            "type": "t_array(t_uint256)40_storage",
            "src": "../project:/contracts/ERC721Upgradeable.sol:494"
          },
          {
            "contract": "ERC721DefaultApproval",
            "label": "defaultApprovals",
            "type": "t_mapping(t_address,t_bool)",
            "src": "../project:/contracts/ERC721DefaultApproval.sol:7"
          },
          {
            "contract": "ERC721DefaultApproval",
            "label": "__gap",
            "type": "t_array(t_uint256)50_storage",
            "src": "../project:/contracts/ERC721DefaultApproval.sol:23"
          },
          {
            "contract": "ERC721BurnableUpgradeable",
            "label": "__gap",
            "type": "t_array(t_uint256)50_storage",
            "src": "../project:/contracts/ERC721BurnableUpgradeable.sol:40"
          },
          {
            "contract": "EIP712Upgradeable",
            "label": "_HASHED_NAME",
            "type": "t_bytes32",
            "src": "../@openzeppelin/contracts-upgradeable/drafts/EIP712Upgradeable.sol:27"
          },
          {
            "contract": "EIP712Upgradeable",
            "label": "_HASHED_VERSION",
            "type": "t_bytes32",
            "src": "../@openzeppelin/contracts-upgradeable/drafts/EIP712Upgradeable.sol:28"
          },
          {
            "contract": "EIP712Upgradeable",
            "label": "__gap",
            "type": "t_array(t_uint256)50_storage",
            "src": "../@openzeppelin/contracts-upgradeable/drafts/EIP712Upgradeable.sol:120"
          },
          {
            "contract": "ERC1271ValidatorForERC721",
            "label": "__gap",
            "type": "t_array(t_uint256)50_storage",
            "src": "../project:/contracts/Mint721Validator.sol:26"
          },
          {
            "contract": "Mint721Validator",
            "label": "__gap",
            "type": "t_array(t_uint256)50_storage",
            "src": "../project:/contracts/Mint721Validator.sol:37"
          },
          {
            "contract": "OwnableUpgradeable",
            "label": "_owner",
            "type": "t_address",
            "src": "../@openzeppelin/contracts-upgradeable/access/OwnableUpgradeable.sol:20"
          },
          {
            "contract": "OwnableUpgradeable",
            "label": "__gap",
            "type": "t_array(t_uint256)49_storage",
            "src": "../@openzeppelin/contracts-upgradeable/access/OwnableUpgradeable.sol:74"
          },
          {
            "contract": "ERC721Lazy",
            "label": "creators",
            "type": "t_mapping(t_uint256,t_address)",
            "src": "../project:/contracts/ERC721Lazy.sol:21"
          },
          {
            "contract": "ERC721Lazy",
            "label": "royaltyFees",
            "type": "t_mapping(t_uint256,t_uint256)",
            "src": "../project:/contracts/ERC721Lazy.sol:22"
          },
          {
            "contract": "ERC721Lazy",
            "label": "metasaltToken",
            "type": "t_address",
            "src": "../project:/contracts/ERC721Lazy.sol:23"
          },
          {
            "contract": "ERC721Lazy",
            "label": "MetasaltTokenCreateRewardValue",
            "type": "t_uint256",
            "src": "../project:/contracts/ERC721Lazy.sol:24"
          },
          {
            "contract": "ERC721Lazy",
            "label": "__gap",
            "type": "t_array(t_uint256)50_storage",
            "src": "../project:/contracts/ERC721Lazy.sol:121"
          },
          {
            "contract": "ERC721Base",
            "label": "__gap",
            "type": "t_array(t_uint256)50_storage",
            "src": "../project:/contracts/ERC721Base.sol:26"
          },
          {
            "contract": "ERC721MetaSalt",
            "label": "__gap",
            "type": "t_array(t_uint256)50_storage",
            "src": "../project:/contracts/ERC721MetaSalt.sol:25"
          }
        ],
        "types": {
          "t_array(t_uint256)50_storage": {
            "label": "uint256[50]"
          },
          "t_uint256": {
            "label": "uint256"
          },
          "t_mapping(t_uint256,t_address)": {
            "label": "mapping(uint256 => address)"
          },
          "t_address": {
            "label": "address"
          },
          "t_mapping(t_uint256,t_uint256)": {
            "label": "mapping(uint256 => uint256)"
          },
          "t_array(t_uint256)49_storage": {
            "label": "uint256[49]"
          },
          "t_bytes32": {
            "label": "bytes32"
          },
          "t_mapping(t_address,t_bool)": {
            "label": "mapping(address => bool)"
          },
          "t_bool": {
            "label": "bool"
          },
          "t_mapping(t_address,t_struct(UintSet)3148_storage)": {
            "label": "mapping(address => struct EnumerableSetUpgradeable.UintSet)"
          },
          "t_struct(UintSet)3148_storage": {
            "label": "struct EnumerableSetUpgradeable.UintSet",
            "members": [
              {
                "label": "_inner",
                "type": "t_struct(Set)2762_storage"
              }
            ]
          },
          "t_struct(Set)2762_storage": {
            "label": "struct EnumerableSetUpgradeable.Set",
            "members": [
              {
                "label": "_values",
                "type": "t_array(t_bytes32)dyn_storage"
              },
              {
                "label": "_indexes",
                "type": "t_mapping(t_bytes32,t_uint256)"
              }
            ]
          },
          "t_array(t_bytes32)dyn_storage": {
            "label": "bytes32[]"
          },
          "t_mapping(t_bytes32,t_uint256)": {
            "label": "mapping(bytes32 => uint256)"
          },
          "t_struct(UintToAddressMap)2525_storage": {
            "label": "struct EnumerableMapUpgradeable.UintToAddressMap",
            "members": [
              {
                "label": "_inner",
                "type": "t_struct(Map)2207_storage"
              }
            ]
          },
          "t_struct(Map)2207_storage": {
            "label": "struct EnumerableMapUpgradeable.Map",
            "members": [
              {
                "label": "_entries",
                "type": "t_array(t_struct(MapEntry)2199_storage)dyn_storage"
              },
              {
                "label": "_indexes",
                "type": "t_mapping(t_bytes32,t_uint256)"
              }
            ]
          },
          "t_array(t_struct(MapEntry)2199_storage)dyn_storage": {
            "label": "struct EnumerableMapUpgradeable.MapEntry[]"
          },
          "t_struct(MapEntry)2199_storage": {
            "label": "struct EnumerableMapUpgradeable.MapEntry",
            "members": [
              {
                "label": "_key",
                "type": "t_bytes32"
              },
              {
                "label": "_value",
                "type": "t_bytes32"
              }
            ]
          },
          "t_mapping(t_address,t_mapping(t_address,t_bool))": {
            "label": "mapping(address => mapping(address => bool))"
          },
          "t_string_storage": {
            "label": "string"
          },
          "t_mapping(t_uint256,t_string_storage)": {
            "label": "mapping(uint256 => string)"
          },
          "t_mapping(t_uint256,t_bool)": {
            "label": "mapping(uint256 => bool)"
          },
          "t_array(t_uint256)40_storage": {
            "label": "uint256[40]"
          },
          "t_mapping(t_bytes4,t_bool)": {
            "label": "mapping(bytes4 => bool)"
          },
          "t_bytes4": {
            "label": "bytes4"
          }
        }
      }
    }
  }
}
